ez_route/__init__.py
ez_route/core/__init__.py
ez_route/core/base.py
ez_route/core/utils.py
ez_route/platform/__init__.py
ez_route/platform/screen_factory.py
ez_route/routing/__init__.py
ez_route/routing/manager.py
ez_route/routing/registry.py
ez_route/routing/route.py
ez_route/routing/route_interpreter.py
ez_route/routing/router.py
ez_route/services/__init__.py
ez_route/services/service_locator.py
ez_route-0.1.1.dist-info/licenses/LICENSE
ez_route-0.1.1.dist-info/METADATA
ez_route-0.1.1.dist-info/WHEEL
ez_route-0.1.1.dist-info/top_level.txt
ez_route-0.1.1.dist-info/RECORD
