Metadata-Version: 2.4
Name: ez-route
Version: 0.1.1
Summary: A lightweight routing system for GUI applications (PyQt, Tkinter, etc.)
Home-page: https://github.com/MyothantTheDev/ez_route
Author: Myo Thant
Author-email: myothant.thedev@gmail.com
Classifier: Programming Language :: Python :: 3
Classifier: License :: OSI Approved :: MIT License
Classifier: Operating System :: OS Independent
Requires-Python: >=3.8
License-File: LICENSE
Provides-Extra: qt
Requires-Dist: PyQt6; extra == "qt"
Provides-Extra: tk
Requires-Dist: tk; extra == "tk"
Dynamic: author
Dynamic: author-email
Dynamic: classifier
Dynamic: description
Dynamic: description-content-type
Dynamic: home-page
Dynamic: license-file
Dynamic: provides-extra
Dynamic: requires-python
Dynamic: summary
